Imagem_processing_chemdexx/__init__.py
Imagem_processing_chemdexx/processing/__init__.py
Imagem_processing_chemdexx/processing/combination.py
Imagem_processing_chemdexx/processing/transformation.py
Imagem_processing_chemdexx/utils/__init__.py
Imagem_processing_chemdexx/utils/io.py
Imagem_processing_chemdexx/utils/plot.py
Imagem_processing_chemdexx-0.0.1.dist-info/METADATA
Imagem_processing_chemdexx-0.0.1.dist-info/WHEEL
Imagem_processing_chemdexx-0.0.1.dist-info/top_level.txt
Imagem_processing_chemdexx-0.0.1.dist-info/RECORD
