Metadata-Version: 2.1
Name: Imagem-processing-chemdexx
Version: 0.0.1
Summary: Image Processing Package using Skimage
Home-page: https://github.com/Chemdexx/Desafio-Criacao-de-Pacotes-Python
Author: Sekine
License: UNKNOWN
Platform: UNKNOWN
Requires-Python: >=3.8
Requires-Dist: matplotlib
Requires-Dist: numpy
Requires-Dist: scikit-image (>=0.16.1)
